tomte/__init__.py
tomte/cli.py
tomte/scripts/check_spelling.sh
tomte/tools/__init__.py
tomte/tools/check_copyright.py
tomte/tools/check_doc_links.py
tomte/tools/check_readme.py
tomte/tools/freeze_dependencies.py
tomte-0.5.0.dist-info/METADATA
tomte-0.5.0.dist-info/WHEEL
tomte-0.5.0.dist-info/entry_points.txt
tomte-0.5.0.dist-info/licenses/LICENSE
tomte-0.5.0.dist-info/RECORD
