Metadata-Version: 2.4
Name: tomte
Version: 0.5.0
Summary: A library that wraps many useful tools (linters, analysers, etc) to keep Python code clean, secure, well-documented and optimised.
License: MIT
License-File: LICENSE
Author: David Minarsch
Author-email: david.minarsch@googlemail.com
Requires-Python: >=3.10,<4
Classifier: License :: OSI Approved :: MIT License
Classifier: Programming Language :: Python :: 3
Classifier: Programming Language :: Python :: 3.10
Classifier: Programming Language :: Python :: 3.11
Classifier: Programming Language :: Python :: 3.12
Classifier: Programming Language :: Python :: 3.13
Classifier: Programming Language :: Python :: 3.14
Provides-Extra: bandit
Provides-Extra: black
Provides-Extra: cli
Provides-Extra: darglint
Provides-Extra: docs
Provides-Extra: flake8
Provides-Extra: isort
Provides-Extra: liccheck
Provides-Extra: mypy
Provides-Extra: pylint
Provides-Extra: safety
Provides-Extra: tests
Provides-Extra: tox
Provides-Extra: vulture
Requires-Dist: Markdown (==3.8.2) ; extra == "docs"
Requires-Dist: Pygments (==2.19.2) ; extra == "docs"
Requires-Dist: bandit (==1.8.6) ; extra == "bandit"
Requires-Dist: black (==25.1.0) ; extra == "black"
Requires-Dist: bs4 (==0.0.2) ; extra == "docs"
Requires-Dist: click (==8.2.1) ; extra == "black" or extra == "cli" or extra == "docs"
Requires-Dist: darglint (==1.8.1) ; extra == "darglint"
Requires-Dist: flake8 (==7.3.0) ; extra == "flake8"
Requires-Dist: flake8-bugbear (==24.12.12) ; extra == "flake8"
Requires-Dist: flake8-docstrings (==1.7.0) ; extra == "flake8"
Requires-Dist: flake8-eradicate (==1.5.0) ; extra == "flake8"
Requires-Dist: flake8-isort (==6.1.2) ; extra == "flake8"
Requires-Dist: flake8-pytest-style (==2.1.0) ; extra == "flake8"
Requires-Dist: isort (==6.0.1) ; extra == "isort"
Requires-Dist: liccheck (==0.9.2) ; extra == "liccheck"
Requires-Dist: markdown-include (==0.8.1) ; extra == "docs"
Requires-Dist: mkdocs (==1.6.1) ; extra == "docs"
Requires-Dist: mkdocs-macros-plugin (==1.3.7) ; extra == "docs"
Requires-Dist: mkdocs-material (==9.6.15) ; extra == "docs"
Requires-Dist: mkdocs-material-extensions (==1.3.1) ; extra == "docs"
Requires-Dist: mkdocs-redirects (==1.2.2) ; extra == "docs"
Requires-Dist: mypy (==1.16.1) ; extra == "mypy"
Requires-Dist: pydoc-markdown (==4.8.2) ; extra == "docs"
Requires-Dist: pydocstyle (==6.3.0) ; extra == "flake8" or extra == "docs"
Requires-Dist: pylint (==3.3.7) ; extra == "pylint"
Requires-Dist: pymdown-extensions (==10.16) ; extra == "docs"
Requires-Dist: pytest (==7.4.4) ; extra == "tests"
Requires-Dist: pytest-asyncio (==0.21.2) ; extra == "tests"
Requires-Dist: pytest-cov (==6.2.1) ; extra == "tests"
Requires-Dist: pytest-randomly (==3.16.0) ; extra == "tests"
Requires-Dist: pytest-rerunfailures (==15.1) ; extra == "tests"
Requires-Dist: requests (==2.32.4) ; extra == "cli"
Requires-Dist: safety (==3.7.0) ; extra == "safety"
Requires-Dist: tox (==4.34.1) ; extra == "cli" or extra == "tox"
Requires-Dist: vulture (==2.14) ; extra == "vulture"
